sock_HTTP_adapter.py
xrzz.py
xrzz-0.1.5.dist-info/LICENSE.txt
xrzz-0.1.5.dist-info/METADATA
xrzz-0.1.5.dist-info/WHEEL
xrzz-0.1.5.dist-info/top_level.txt
xrzz-0.1.5.dist-info/RECORD
