Metadata-Version: 2.1
Name: xrzz
Version: 0.1.5
Summary: HTTP Request from scratch 101
Home-page: https://www.youtube.com/c/FunnyBunny-YT
Author: dedshit
Author-email: crapholy040@gmail.com
License: UNKNOWN
Platform: UNKNOWN
Classifier: Programming Language :: Python :: 3
Classifier: Programming Language :: Python :: 3.7
Classifier: Programming Language :: Python :: 3.9
Classifier: License :: OSI Approved :: GNU General Public License v2 or later (GPLv2+)
Classifier: Operating System :: OS Independent
